{"nodes": [{"id": "esnad_src_pages_public_publicationpage_tsx", "label": "PublicationPage.tsx", "file_type": "code", "source_file": "esnad\\src\\pages\\public\\PublicationPage.tsx", "source_location": "L1"}, {"id": "publicationpage_handlesavetoggle", "label": "handleSaveToggle()", "file_type": "code", "source_file": "esnad\\src\\pages\\public\\PublicationPage.tsx", "source_location": "L72"}, {"id": "publicationpage_handlepurchase", "label": "handlePurchase()", "file_type": "code", "source_file": "esnad\\src\\pages\\public\\PublicationPage.tsx", "source_location": "L91"}, {"id": "publicationpage_sharetowhatsapp", "label": "shareToWhatsApp()", "file_type": "code", "source_file": "esnad\\src\\pages\\public\\PublicationPage.tsx", "source_location": "L127"}, {"id": "publicationpage_sharetotwitter", "label": "shareToTwitter()", "file_type": "code", "source_file": "esnad\\src\\pages\\public\\PublicationPage.tsx", "source_location": "L133"}, {"id": "publicationpage_sharetofacebook", "label": "shareToFacebook()", "file_type": "code", "source_file": "esnad\\src\\pages\\public\\PublicationPage.tsx", "source_location": "L139"}, {"id": "publicationpage_sharetoinstagram", "label": "shareToInstagram()", "file_type": "code", "source_file": "esnad\\src\\pages\\public\\PublicationPage.tsx", "source_location": "L145"}, {"id": "publicationpage_copysharelink", "label": "copyShareLink()", "file_type": "code", "source_file": "esnad\\src\\pages\\public\\PublicationPage.tsx", "source_location": "L159"}], "edges": [{"source": "esnad_src_pages_public_publicationpage_tsx", "target": "react", "relation": "imports_from", "confidence": "EXTRACTED", "source_file": "esnad\\src\\pages\\public\\PublicationPage.tsx", "source_location": "L1", "weight": 1.0}, {"source": "esnad_src_pages_public_publicationpage_tsx", "target": "react_router_dom", "relation": "imports_from", "confidence": "EXTRACTED", "source_file": "esnad\\src\\pages\\public\\PublicationPage.tsx", "source_location": "L2", "weight": 1.0}, {"source": "esnad_src_pages_public_publicationpage_tsx", "target": "esnad_src_pages_public_components_public_publicationcard", "relation": "imports_from", "confidence": "EXTRACTED", "source_file": "esnad\\src\\pages\\public\\PublicationPage.tsx", "source_location": "L3", "weight": 1.0}, {"source": "esnad_src_pages_public_publicationpage_tsx", "target": "esnad_src_pages_public_components_public_publicsiteshell", "relation": "imports_from", "confidence": "EXTRACTED", "source_file": "esnad\\src\\pages\\public\\PublicationPage.tsx", "source_location": "L4", "weight": 1.0}, {"source": "esnad_src_pages_public_publicationpage_tsx", "target": "esnad_src_pages_public_contexts_publicsessioncontext", "relation": "imports_from", "confidence": "EXTRACTED", "source_file": "esnad\\src\\pages\\public\\PublicationPage.tsx", "source_location": "L5", "weight": 1.0}, {"source": "esnad_src_pages_public_publicationpage_tsx", "target": "esnad_src_pages_public_lib_firebase", "relation": "imports_from", "confidence": "EXTRACTED", "source_file": "esnad\\src\\pages\\public\\PublicationPage.tsx", "source_location": "L6", "weight": 1.0}, {"source": "esnad_src_pages_public_publicationpage_tsx", "target": "esnad_src_pages_public_lib_library", "relation": "imports_from", "confidence": "EXTRACTED", "source_file": "esnad\\src\\pages\\public\\PublicationPage.tsx", "source_location": "L7", "weight": 1.0}, {"source": "esnad_src_pages_public_publicationpage_tsx", "target": "esnad_src_pages_public_lib_navigation", "relation": "imports_from", "confidence": "EXTRACTED", "source_file": "esnad\\src\\pages\\public\\PublicationPage.tsx", "source_location": "L8", "weight": 1.0}, {"source": "esnad_src_pages_public_publicationpage_tsx", "target": "esnad_src_pages_public_lib_payments", "relation": "imports_from", "confidence": "EXTRACTED", "source_file": "esnad\\src\\pages\\public\\PublicationPage.tsx", "source_location": "L9", "weight": 1.0}, {"source": "esnad_src_pages_public_publicationpage_tsx", "target": "esnad_src_pages_public_reader_lib_render_pm_json", "relation": "imports_from", "confidence": "EXTRACTED", "source_file": "esnad\\src\\pages\\public\\PublicationPage.tsx", "source_location": "L10", "weight": 1.0}, {"source": "esnad_src_pages_public_publicationpage_tsx", "target": "esnad_src_pages_public_lib_publications", "relation": "imports_from", "confidence": "EXTRACTED", "source_file": "esnad\\src\\pages\\public\\PublicationPage.tsx", "source_location": "L11", "weight": 1.0}, {"source": "esnad_src_pages_public_publicationpage_tsx", "target": "esnad_src_pages_public_lib_sitelinks", "relation": "imports_from", "confidence": "EXTRACTED", "source_file": "esnad\\src\\pages\\public\\PublicationPage.tsx", "source_location": "L25", "weight": 1.0}, {"source": "esnad_src_pages_public_publicationpage_tsx", "target": "esnad_src_pages_public_types_publication", "relation": "imports_from", "confidence": "EXTRACTED", "source_file": "esnad\\src\\pages\\public\\PublicationPage.tsx", "source_location": "L26", "weight": 1.0}, {"source": "esnad_src_pages_public_publicationpage_tsx", "target": "publicationpage_handlesavetoggle", "relation": "contains", "confidence": "EXTRACTED", "source_file": "esnad\\src\\pages\\public\\PublicationPage.tsx", "source_location": "L72", "weight": 1.0}, {"source": "esnad_src_pages_public_publicationpage_tsx", "target": "publicationpage_handlepurchase", "relation": "contains", "confidence": "EXTRACTED", "source_file": "esnad\\src\\pages\\public\\PublicationPage.tsx", "source_location": "L91", "weight": 1.0}, {"source": "esnad_src_pages_public_publicationpage_tsx", "target": "publicationpage_sharetowhatsapp", "relation": "contains", "confidence": "EXTRACTED", "source_file": "esnad\\src\\pages\\public\\PublicationPage.tsx", "source_location": "L127", "weight": 1.0}, {"source": "esnad_src_pages_public_publicationpage_tsx", "target": "publicationpage_sharetotwitter", "relation": "contains", "confidence": "EXTRACTED", "source_file": "esnad\\src\\pages\\public\\PublicationPage.tsx", "source_location": "L133", "weight": 1.0}, {"source": "esnad_src_pages_public_publicationpage_tsx", "target": "publicationpage_sharetofacebook", "relation": "contains", "confidence": "EXTRACTED", "source_file": "esnad\\src\\pages\\public\\PublicationPage.tsx", "source_location": "L139", "weight": 1.0}, {"source": "esnad_src_pages_public_publicationpage_tsx", "target": "publicationpage_sharetoinstagram", "relation": "contains", "confidence": "EXTRACTED", "source_file": "esnad\\src\\pages\\public\\PublicationPage.tsx", "source_location": "L145", "weight": 1.0}, {"source": "esnad_src_pages_public_publicationpage_tsx", "target": "publicationpage_copysharelink", "relation": "contains", "confidence": "EXTRACTED", "source_file": "esnad\\src\\pages\\public\\PublicationPage.tsx", "source_location": "L159", "weight": 1.0}]}